{
    "Basic": {
        "checkpoints": [
            {
                "steps": 499997,
                "file_path": "results\\0_Pipeline\\Jump\\PPO\\Run_4\\Basic\\Basic-499997.onnx",
                "reward": 1.0865807801485061,
                "creation_time": 1618303988.6115525
            },
            {
                "steps": 999998,
                "file_path": "results\\0_Pipeline\\Jump\\PPO\\Run_4\\Basic\\Basic-999998.onnx",
                "reward": 1.083106231748719,
                "creation_time": 1618305940.5974486
            },
            {
                "steps": 1024005,
                "file_path": "results\\0_Pipeline\\Jump\\PPO\\Run_4\\Basic\\Basic-1024005.onnx",
                "reward": 1.062202714677704,
                "creation_time": 1618306034.6282535
            }
        ],
        "final_checkpoint": {
            "steps": 1024005,
            "file_path": "results\\0_Pipeline\\Jump\\PPO\\Run_4\\Basic.onnx",
            "reward": 1.062202714677704,
            "creation_time": 1618306034.6282535
        }
    },
    "metadata": {
        "stats_format_version": "0.2.0",
        "mlagents_version": "0.25.0",
        "torch_version": "1.8.1+cpu"
    }
}