{
    "Basic": {
        "checkpoints": [
            {
                "steps": 12598,
                "file_path": "results\\0_Pipeline\\Jump\\SAC_256\\Run_0\\Basic\\Basic-12598.onnx",
                "reward": null,
                "creation_time": 1618448688.146899
            }
        ],
        "final_checkpoint": {
            "steps": 12598,
            "file_path": "results\\0_Pipeline\\Jump\\SAC_256\\Run_0\\Basic.onnx",
            "reward": null,
            "creation_time": 1618448688.146899
        }
    },
    "metadata": {
        "stats_format_version": "0.2.0",
        "mlagents_version": "0.25.0",
        "torch_version": "1.8.1"
    }
}